opencollective_export/__init__.py
opencollective_export/main.py
opencollective_export/opencollective.py
opencollective_export-1.0.0.dist-info/METADATA
opencollective_export-1.0.0.dist-info/WHEEL
opencollective_export-1.0.0.dist-info/entry_points.txt
opencollective_export-1.0.0.dist-info/licenses/LICENSE
opencollective_export-1.0.0.dist-info/RECORD
