Metadata-Version: 2.4
Name: opencollective-export
Version: 1.0.0
Summary: A simple CLI tool to export backer data from Open Collective.
License-File: LICENSE
Requires-Python: >=3.12
Requires-Dist: cyclopts>=4.4.4
Requires-Dist: gql[aiohttp,websockets]>=4.0.0
Requires-Dist: keyring>=25.7.0
Requires-Dist: rich>=14.2.0
